CHANGELOG.rst
LICENSE
MANIFEST.in
README.md
fedimg-conf.toml.example
mkdocs.yml
setup.cfg
setup.py
docs/.index.rst.swp
docs/Makefile
docs/conf.py
docs/index.rst
docs/release_notes.rst
docs/_build/doctrees/contributing.doctree
docs/_build/doctrees/contribution.doctree
docs/_build/doctrees/environment.pickle
docs/_build/doctrees/index.doctree
docs/_build/doctrees/installation.doctree
docs/_build/doctrees/release_notes.doctree
docs/_build/doctrees/architecture/configuration.doctree
docs/_build/doctrees/architecture/consumer.doctree
docs/_build/doctrees/development/contribution.doctree
docs/_build/doctrees/development/installation.doctree
docs/_build/doctrees/development/testing.doctree
docs/_build/html/.buildinfo
docs/_build/html/contributing.html
docs/_build/html/contribution.html
docs/_build/html/genindex.html
docs/_build/html/index.html
docs/_build/html/installation.html
docs/_build/html/objects.inv
docs/_build/html/release_notes.html
docs/_build/html/search.html
docs/_build/html/searchindex.js
docs/_build/html/_sources/contributing.txt
docs/_build/html/_sources/contribution.txt
docs/_build/html/_sources/index.txt
docs/_build/html/_sources/installation.txt
docs/_build/html/_sources/release_notes.txt
docs/_build/html/_sources/architecture/configuration.txt
docs/_build/html/_sources/architecture/consumer.txt
docs/_build/html/_sources/development/contribution.txt
docs/_build/html/_sources/development/installation.txt
docs/_build/html/_sources/development/testing.txt
docs/_build/html/_static/ajax-loader.gif
docs/_build/html/_static/alabaster.css
docs/_build/html/_static/basic.css
docs/_build/html/_static/comment-bright.png
docs/_build/html/_static/comment-close.png
docs/_build/html/_static/comment.png
docs/_build/html/_static/custom.css
docs/_build/html/_static/doctools.js
docs/_build/html/_static/down-pressed.png
docs/_build/html/_static/down.png
docs/_build/html/_static/file.png
docs/_build/html/_static/jquery-1.11.1.js
docs/_build/html/_static/jquery.js
fedimg.egg-info/PKG-INFO
fedimg.egg-info/SOURCES.txt
fedimg.egg-info/dependency_links.txt
fedimg.egg-info/entry_points.txt
fedimg.egg-info/not-zip-safe
fedimg.egg-info/pbr.json
fedimg.egg-info/requires.txt
fedimg.egg-info/top_level.txt
