Metadata-Version: 1.1
Name: fedimg
Version: 2.4.0
Summary: Automatically upload Fedora Cloud images to cloud providers
Home-page: https://github.com/fedora-infra/fedimg
Author: Fedora Infrastructure Team
Author-email: infrastructure@lists.fedoraproject.org
License: AGPLv3+
Keywords: python Fedora cloud image uploader service
Platform: UNKNOWN
Classifier: Programming Language :: Python :: 2.7
Classifier: License :: OSI Approved :: GNU Affero General Public License v3 or later (AGPLv3+)
